hypermedia/__init__.py
hypermedia/audio_and_video.py
hypermedia/basic.py
hypermedia/fastapi.py
hypermedia/formatting.py
hypermedia/forms_and_input.py
hypermedia/frames.py
hypermedia/images.py
hypermedia/links.py
hypermedia/lists.py
hypermedia/meta_info.py
hypermedia/programming.py
hypermedia/py.typed
hypermedia/styles_and_semantics.py
hypermedia/tables.py
hypermedia/models/__init__.py
hypermedia/models/base.py
hypermedia/models/elements.py
hypermedia/types/__init__.py
hypermedia/types/attributes.py
hypermedia/types/styles.py
hypermedia/types/types.py
hypermedia-5.4.0.dist-info/METADATA
hypermedia-5.4.0.dist-info/WHEEL
hypermedia-5.4.0.dist-info/licenses/LICENSE
hypermedia-5.4.0.dist-info/RECORD
