Metadata-Version: 2.4
Name: hypermedia
Version: 5.4.0
Summary: An opinionated way to work with html in pure python with htmx support.
Project-URL: Homepage, https://github.com/thomasborgen/hypermedia
Project-URL: Documentation, https://github.com/thomasborgen/hypermedia
Project-URL: Repository, https://github.com/thomasborgen/hypermedia
Project-URL: Changelog, https://github.com/thomasborgen/hypermedia/blob/main/CHANGELOG.md
Author-email: Thomas Borgen <thomas@borgenit.no>
License: MIT
License-File: LICENSE
Keywords: Extendable,FastAPI,HTML,HTML Templating,HTMX,Partial HTML
Requires-Python: >=3.9
Requires-Dist: typing-extensions>=4.12.2
